AUTHORS
ChangeLog
README.md
example.py
requirements.txt
setup.cfg
setup.py
simple_rpc/__init__.py
simple_rpc/simple_rpc.js
simple_rpc.egg-info/PKG-INFO
simple_rpc.egg-info/SOURCES.txt
simple_rpc.egg-info/dependency_links.txt
simple_rpc.egg-info/not-zip-safe
simple_rpc.egg-info/pbr.json
simple_rpc.egg-info/requires.txt
simple_rpc.egg-info/top_level.txt
tests/__init__.py
tests/python_test.py