Metadata-Version: 1.0
Name: simple-rpc
Version: 1.0.2
Summary: RPC without complications.
Home-page: https://github.com/chrisnorman7/
Author: Chris Norman
Author-email: chris.norman2@googlemail.com
License: MPL-2
Platform: UNKNOWN
